[
    {
        "q_id" : "q1",
        "text" : "What's up?",
        "answers" : [
            {
                "value" : 1,
                "text" : "Hello1"
            },
            {
                "value" : 2,
                "text" : "Hello2"
            },
            {
                "value" : 3,
                "text" : "Hello3"
            }
        ]
    },
    {
        "q_id" : "q2",
        "text" : "What's up 2?",
        "answers" : [
            {
                "value" : 1,
                "text" : "Ho1"
            },
            {
                "value" : 2,
                "text" : "Hu2"
            },
            {
                "value" : 3,
                "text" : "Hello3"
            }
        ]
    }
]